seekwellpandas/__init__.py
seekwellpandas/aggregate.py
seekwellpandas/alias.py
seekwellpandas/conditional.py
seekwellpandas/errors.py
seekwellpandas/filtering.py
seekwellpandas/grouping.py
seekwellpandas/joins.py
seekwellpandas/methods.py
seekwellpandas/miscellaneous.py
seekwellpandas/query_wrapper.py
seekwellpandas/selection.py
seekwellpandas/sorting.py
seekwellpandas/window_functions.py
seekwellpandas-0.3.0.dist-info/licenses/LICENSE
seekwellpandas-0.3.0.dist-info/METADATA
seekwellpandas-0.3.0.dist-info/WHEEL
seekwellpandas-0.3.0.dist-info/top_level.txt
seekwellpandas-0.3.0.dist-info/RECORD
