Metadata-Version: 2.4
Name: seekwellpandas
Version: 0.3.0
Summary: SQL queries on Pandas data frames
Author-email: Essi Parent <9ivko1ozf@relay.firefox.com>
Project-URL: Homepage, https://github.com/essicolo/seekwellpandas
Project-URL: Bug Tracker, https://github.com/essicolo/seekwellpandas/issues
Classifier: Programming Language :: Python :: 3
Classifier: License :: OSI Approved :: GNU General Public License v3 (GPLv3)
Classifier: Operating System :: OS Independent
Requires-Python: >=3.7
License-File: LICENSE
Requires-Dist: pandas>=2.0.0
Requires-Dist: pandas-flavor>=0.3.0
Provides-Extra: dev
Requires-Dist: bump-my-version; extra == "dev"
Requires-Dist: marimo; extra == "dev"
Requires-Dist: uv; extra == "dev"
Dynamic: license-file
